inseis/__init__.py
inseis/__main__.py
inseis/config/__init__.py
inseis/config/settings.py
inseis/core/__init__.py
inseis/core/process_manager.py
inseis/core/workflow_manager.py
inseis/data/__init__.py
inseis/data/process_definitions/basic_processes.json
inseis/data/process_definitions/segyclean.json
inseis/data/process_definitions/segyread.json
inseis/data/process_definitions/suacor.json
inseis/data/process_definitions/suaddnoise.json
inseis/data/process_definitions/subfilt.json
inseis/data/process_definitions/sucat.json
inseis/data/process_definitions/sufilter.json
inseis/data/process_definitions/sufrac.json
inseis/data/process_definitions/sufxdecon.json
inseis/data/process_definitions/sugain.json
inseis/data/process_definitions/sugazmigq.json
inseis/data/process_definitions/suinterp.json
inseis/data/process_definitions/sukdmig2d.json
inseis/data/process_definitions/suktmig2d.json
inseis/data/process_definitions/sumedian.json
inseis/data/process_definitions/sumigfd.json
inseis/data/process_definitions/sumigffd.json
inseis/data/process_definitions/sumiggbzo.json
inseis/data/process_definitions/sumigps.json
inseis/data/process_definitions/sumix.json
inseis/data/process_definitions/sunormalize.json
inseis/data/process_definitions/suop2.json
inseis/data/process_definitions/supef.json
inseis/data/process_definitions/suradon.json
inseis/data/process_definitions/sustolt.json
inseis/data/process_definitions/sutaup.json
inseis/data/process_definitions/suttoz.json
inseis/data/process_definitions/sutvband.json
inseis/ui/__init__.py
inseis/ui/dialogs.py
inseis/ui/main_window.py
inseis/ui/panels.py
inseis/ui/theme.qss
inseis/ui/visualization.py
inseis/ui/workflow_controller.py
inseis/utils/__init__.py
inseis/utils/console.py
inseis/utils/path_utils.py
inseis/utils/resources.py
inseis/utils/result.py
inseis-1.1.1.dist-info/licenses/LICENSE
inseis-1.1.1.dist-info/METADATA
inseis-1.1.1.dist-info/WHEEL
inseis-1.1.1.dist-info/entry_points.txt
inseis-1.1.1.dist-info/top_level.txt
inseis-1.1.1.dist-info/RECORD
