Metadata-Version: 2.4
Name: inseis
Version: 1.1.1
Summary: A GUI-based application for creating and running Seismic Unix workflows on Windows using the Linux subsystem
Author-email: Alejandro Pertuz <apertuz@ucm.es>
Project-URL: Documentation, https://a-pertuz.github.io/REVSEIS/index.html
Project-URL: Source Code, https://github.com/a-pertuz/InSeis
Project-URL: DOI, https://doi.org/10.5281/zenodo.15053545
Keywords: seismic,processing,segy,geophysics,seismic unix
Classifier: Programming Language :: Python :: 3
Classifier: License :: OSI Approved :: GNU General Public License v3 (GPLv3)
Classifier: Operating System :: Microsoft :: Windows
Classifier: Development Status :: 5 - Production/Stable
Classifier: Intended Audience :: Science/Research
Classifier: Programming Language :: Python :: 3.10
Requires-Python: >=3.9
License-File: LICENSE
Requires-Dist: PySide6>=6.8
Requires-Dist: appdirs>=1.4.4
Requires-Dist: matplotlib>=3.7.0
Requires-Dist: seisio>=1.2.0
Requires-Dist: seisplot>=1.2.0
Requires-Dist: setuptools>=65.0.0
Dynamic: license-file
